{"assets/images/about.png":["assets/images/about.png"],"assets/images/accountscreen.jpg":["assets/images/accountscreen.jpg"],"assets/images/bg.png":["assets/images/bg.png"],"assets/images/firstbox.png":["assets/images/firstbox.png"],"assets/images/firstscreen.png":["assets/images/firstscreen.png"],"assets/images/fourthbox.png":["assets/images/fourthbox.png"],"assets/images/homescreencover.png":["assets/images/homescreencover.png"],"assets/images/popularcourses.png":["assets/images/popularcourses.png"],"assets/images/secondbox.png":["assets/images/secondbox.png"],"assets/images/secondscreen.png":["assets/images/secondscreen.png"],"assets/images/text.png":["assets/images/text.png"],"assets/images/thirdbox.png":["assets/images/thirdbox.png"],"packages/cupertino_icons/assets/CupertinoIcons.ttf":["packages/cupertino_icons/assets/CupertinoIcons.ttf"]}